LICENSE.txt
README.md
setup.py
turbie_bruno/Functions_CodeCamp_Project.py
turbie_bruno/Turbie_run.py
turbie_bruno/__init__.py
turbie_bruno.egg-info/PKG-INFO
turbie_bruno.egg-info/SOURCES.txt
turbie_bruno.egg-info/dependency_links.txt
turbie_bruno.egg-info/top_level.txt