Metadata-Version: 2.1
Name: turbie-bruno
Version: 1.0
Summary: necessary functions to run the DTU turbie model
Author: bruno
License-File: LICENSE.txt
